{
  "声母映射": {
    "b": "波",
    "p": "坡",
    "m": "摸",
    "f": "佛",
    "d": "得",
    "t": "特",
    "n": "讷",
    "l": "了",
    "g": "哥",
    "k": "科",
    "h": "喝",
    "j": "基",
    "q": "七",
    "x": "西",
    "zh": "知",
    "ch": "蚩",
    "sh": "狮",
    "r": "儿",
    "z": "资",
    "c": "雌",
    "s": "思",
    "y": "衣",
    "w": "乌"
  },
  "韵母映射": {
    "a": "啊",
    "ā": "啊",
    "á": "啊",
    "ǎ": "啊",
    "à": "啊",
    "o": "喔",
    "ō": "哦",
    "ó": "哦",
    "ǒ": "哦",
    "ò": "哦",
    "e": "鹅",
    "ē": "诶",
    "é": "诶",
    "ě": "诶",
    "è": "诶",
    "i": "一",
    "ī": "衣",
    "í": "衣",
    "ǐ": "衣",
    "ì": "衣",
    "u": "乌",
    "ū": "乌",
    "ú": "乌",
    "ǔ": "乌",
    "ù": "乌",
    "ü": "迂",
    "ǖ": "鱼",
    "ǘ": "鱼",
    "ǚ": "鱼",
    "ǜ": "鱼",
    "ai": "哀",
    "āi": "哀",
    "ái": "埃",
    "ǎi": "矮",
    "ài": "爱",
    "ei": "诶",
    "ēi": "诶",
    "éi": "诶",
    "ěi": "诶",
    "èi": "诶",
    "ui": "威",
    "uī": "威",
    "uí": "威",
    "uǐ": "尾",
    "uì": "畏",
    "ao": "袄",
    "āo": "熬",
    "áo": "熬",
    "ǎo": "袄",
    "ào": "奥",
    "ou": "偶",
    "ōu": "欧",
    "óu": "偶",
    "ǒu": "偶",
    "òu": "偶",
    "iu": "优",
    "iū": "悠",
    "iú": "油",
    "iǔ": "有",
    "iù": "又",
    "ie": "耶",
    "iē": "椰",
    "ié": "爷",
    "iě": "也",
    "iè": "夜",
    "üe": "约",
    "ǖe": "靴",
    "ǘe": "学",
    "ǚe": "雪",
    "ǜe": "月",
    "iao": "腰",
    "iāo": "腰",
    "iáo": "摇",
    "iǎo": "一袄",
    "iào": "要",
    "uai": "歪",
    "uāi": "歪",
    "uái": "外",
    "uǎi": "拐",
    "uài": "坏",
    "uei": "威",
    "uēi": "威",
    "uéi": "为",
    "uěi": "委",
    "uèi": "位",
    "ian": "烟",
    "iān": "烟",
    "ián": "严",
    "iǎn": "眼",
    "iàn": "雁",
    "uan": "弯",
    "uān": "弯",
    "uán": "完",
    "uǎn": "晚",
    "uàn": "万",
    "üan": "冤",
    "ǖan": "冤",
    "ǘan": "元",
    "ǚan": "远",
    "ǜan": "院",
    "iang": "央",
    "iāng": "央",
    "iáng": "羊",
    "iǎng": "养",
    "iàng": "样",
    "uang": "汪",
    "uāng": "汪",
    "uáng": "王",
    "uǎng": "往",
    "uàng": "旺",
    "iong": "雍",
    "iōng": "雍",
    "ióng": "永",
    "iǒng": "用",
    "iòng": "泳",
    "an": "安",
    "ān": "安",
    "án": "安",
    "ǎn": "俺",
    "àn": "暗",
    "en": "嗯",
    "ēn": "恩",
    "én": "嗯",
    "ěn": "嗯",
    "èn": "嗯",
    "in": "因",
    "īn": "音",
    "ín": "银",
    "ǐn": "引",
    "ìn": "印",
    "un": "温",
    "ūn": "温",
    "ún": "文",
    "ǔn": "稳",

    "ün": "晕",
    "ǖn": "云",
    "ǘn": "云",
    "ǚn": "允",
    "ǜn": "运",
    "ang": "昂",
    "āng": "昂",
    "áng": "昂",
    "ǎng": "昂",
    "àng": "昂",
    "eng": "亨",
    "ēng": "亨",
    "éng": "亨",
    "ěng": "亨",
    "èng": "亨",
    "ing": "英",
    "īng": "鹰",
    "íng": "营",
    "ǐng": "影",
    "ìng": "应",
    "ong": "翁",
    "ōng": "翁",
    "óng": "翁",
    "ǒng": "翁",
    "òng": "翁",
    "er": "儿",
    "ér": "而",
    "ěr": "耳",
    "èr": "二",
    "uǒ": "我",
    "uè": "越",
    "ūè": "曰",
    "úè": "跃",
    "ǔè": "月",
    "ùè": "阅",
    "chè": "屮",
    "zì": "自",
    "yá": "牙",
    "zhǎo": "爪",
    "nèi": "内",
    "wài": "外",
    "chuān": "川",
    "jǐng": "井",
    "yú": "鱼",
    "gōng": "工",
    "chǎng": "厂"
  }
}